WarioEditor/RunPipeline.py
WarioEditor/WarioEditor.py
WarioEditor/__init__.py
WarioEditor/__main__.py
WarioEditor/editorConfig.json
WarioEditor/docs/Makefile
WarioEditor/docs/conf.py
WarioEditor/docs/index.rst
WarioEditor/docs/make.bat
WarioEditor/docs/requirements.txt
WarioEditor/docs/Images/EEGExample.gif
WarioEditor/docs/Images/New Text Document.txt
WarioEditor/docs/Images/WARIO_example.png
WarioEditor/docs/Images/activatedToolkits.gif
WarioEditor/docs/Images/attribTooltip.gif
WarioEditor/docs/Images/connectionGrey.gif
WarioEditor/docs/Images/createConnection.gif
WarioEditor/docs/Images/createNewNode.gif
WarioEditor/docs/Images/globalExample.png
WarioEditor/docs/Images/globalNodes.png
WarioEditor/docs/Images/globalToolkits.png
WarioEditor/docs/Images/globalWindow.png
WarioEditor/docs/Images/toolkitsWindow.png
WarioEditor/docs/Images/visibleToolkits.png
WarioEditor/docs/_build/.buildinfo
WarioEditor/docs/_build/genindex.html
WarioEditor/docs/_build/index.html
WarioEditor/docs/_build/objects.inv
WarioEditor/docs/_build/search.html
WarioEditor/docs/_build/searchindex.js
WarioEditor/docs/_build/.doctrees/environment.pickle
WarioEditor/docs/_build/.doctrees/index.doctree
WarioEditor/docs/_build/.doctrees/developer/globals.doctree
WarioEditor/docs/_build/.doctrees/developer/nodes.doctree
WarioEditor/docs/_build/.doctrees/developer/settings.doctree
WarioEditor/docs/_build/.doctrees/developer/toolkits.doctree
WarioEditor/docs/_build/.doctrees/nodes/utility.doctree
WarioEditor/docs/_build/.doctrees/nodes/utility/mergeLists.doctree
WarioEditor/docs/_build/.doctrees/user/globals.doctree
WarioEditor/docs/_build/.doctrees/user/installation.doctree
WarioEditor/docs/_build/.doctrees/user/pipeline.doctree
WarioEditor/docs/_build/.doctrees/user/toolkits.doctree
WarioEditor/docs/_build/.doctrees/user/userGuide.doctree
WarioEditor/docs/_build/_images/EEGExample.gif
WarioEditor/docs/_build/_images/WARIO_example.png
WarioEditor/docs/_build/_images/activatedToolkits.gif
WARIO_Editor-0.1.2.dist-info/LICENSE.txt
WARIO_Editor-0.1.2.dist-info/METADATA
WARIO_Editor-0.1.2.dist-info/WHEEL
WARIO_Editor-0.1.2.dist-info/top_level.txt
WARIO_Editor-0.1.2.dist-info/RECORD
