Metadata-Version: 2.1
Name: WARIO-Editor
Version: 0.1.2
Summary: Pipeline editor and front end for WARIO
Home-page: https://github.com/McMasterRS/WARIO-Editor
Author: Thomas Mudway, Oliver Cook, Ron Harwood
License: UNKNOWN
Platform: UNKNOWN
Classifier: Programming Language :: Python :: 3
Classifier: License :: OSI Approved :: MIT License
Classifier: Operating System :: OS Independent
Requires-Python: >=3.6
Requires-Dist: PyQt5
Requires-Dist: PyQtWebEngine
Requires-Dist: blinker
Requires-Dist: wario
